{
	"toplevel" : {
		"type" : "menu",
		"data" : {
			"title" : "MASTERS",
			"items" : [
			
				
						{
							"type" : "profile",
							"data" : {
								"title": "INDIAN WELLS",
								"image": "stats/images/15.jpg",
								"body": "The BNP Paribas Open is the first of nine ATP World Tour Masters 1000 events and is held in the small city of Indian Wells, California.\n\nThe 12-day tournament is the best attended tennis event outside the four Grand Slams.\n\nIn 2009, 332,498 spectators passed through the gates, eclipsing the mark set the previous year when it became the first tournament outside of the Grand Slams to pass the 300,000 mark.\n\nPast Winners\n\n2011 Novak Djokovic bt. Rafael Nadal 4-6 6-3 6-2\n2010  Ivan Ljubicic bt. Andy Roddick 7-6 7-6\n2009  Rafael Nadal bt. Andy Murray 6-1, 6-2\n2008  Novak Djokovic bt. Mardy Fish 6-2, 5-7, 6-3\n2007  Rafael Nadal bt. Novak Djokovic 6-2, 7-5\n2006  Roger Federer bt. James Blake 7-5, 6-3, 6-0\n2005  Roger Federer bt. Lleyton Hewitt 6-2, 6-4, 6-4\n2004  Roger Federer bt. Tim Henman 6-3, 6-3\n2003  Lleyton Hewitt bt. Gustavo Kuerten 6-1, 6-1\n2002  Lleyton Hewitt bt. Tim Henman 6-1, 6-2\n2001  Andre Agassi bt. Pete Sampras 7-6, 7-5, 6-1\n2000  lex Corretja bt. Thomas Enqvist 6-4, 6-4, 6-3",
								"stats": [
										{
											"title": "BEGAN",
											"body": "1987"
										},
										{
											"title": "DATE",
											"body": "8-18 MARCH '12"
										},
										{
											"title": "SURFACE",
											"body": "HARD"
										},
										{
											"title": "PRIZE MONEY",
											"body": "$3,645,000"
										},
										{
											"title": "CURRENT HOLDER",
											"body": "NOVAK DJOKOVIC"
										}
									]
							}
						},
				
				
			
				
				
				
				
				
			
			
				
						{
							"type" : "profile",
							"data" : {
								"title": "MIAMI",
								"image": "stats/images/17.jpg",
								"body": "The 12-day Sony Ericsson Open in Miami was voted by the players as the ATP World Tour Masters 1000 tournament of the year for the fifth time in the past six seasons.\n\nPast Winners\n\n2011 Novak Djokovic bt. Rafael Nadal 4-6 6-3 7-6\n2010  Andy Roddick bt. Tomas Berdych 7-5, 6-4\n2009  Andy Murray bt. Novak Djokovic 6-2, 7-5\n2008  Nikolay Davydenko bt. Rafael Nadal 6-4, 6-2\n2007  Novak Djokovic bt. Guillermo Canas 6-3, 6-2, 6-4\n2006  Roger Federer bt. Ivan Ljubicic 7-6, 7-6, 7-6\n2005  Roger Federer bt. Rafael Nadal 2-6, 6-7, 7-6, 6-3, 6-1\n2004  Andy Roddick bt. Guillermo Coria 6-7, 6-3, 6-1, retired\n2003  Andre Agassi bt. Carlos Moya 6-3, 6-3\n2002  Andre Agassi bt. Roger Federer 6-3, 6-3, 3-6, 6-4\n2001  Andre Agassi bt. Jan-Michael Gambill 7-6, 6-1, 6-0\n2000  Pete Sampras bt. Gustavo Kuerten 6-1, 6-7, 7-6, 7-6",
								"stats": [
									]
							}
						},
				
				
			
				
				
				
				
				
			
			
				
						{
							"type" : "profile",
							"data" : {
								"title": "MONTE CARLO",
								"image": "stats/images/22.jpg",
								"body": "The Monte-Carlo Rolex Masters, which celebrated its 100th anniversary in 2006, is the first of three ATP World Tour Masters 1000 tournaments played on clay. Past winners include Bjorn Borg, Thomas Muster, Gustavo Kuerten, Juan Carlos Ferrero and Rafael Nadal.\n\nPast Winners\n\n2013 Stan Wawrinka bt. David Ferrer 6-1 7-6 (3)\n2013 Novak Djokovic bt. Rafael Nadal 6-2, 7-6 (1)\n2012 Rafael Nadal bt. Novak Djokovic 6-3, 6-1\n2011 Rafael Nadal bt. David Ferrer 6-4, 7-5\n2010  Rafael Nadal bt. Fernando Verdasco 6-0, 6-1\n2009  Rafael Nadal bt. Novak Djokovic 6-3, 2-6, 6-1\n2008  Rafael Nadal bt. Roger Federer 7-5, 7-5\n2007  Rafael Nadal bt. Roger Federer 6-4, 6-4\n2006  Rafael Nadal bt. Roger Federer 6-2, 6-7, 6-3, 7-6\n2005  Rafael Nadal bt. Guillermo Coria 6-3, 6-1, 0-6, 7-5\n2004  Guillermo Coria bt. Rainer Schuttler 6-2, 6-1, 6-3\n2003  Juan Carlos Ferrero bt. Guillermo Coria 6-2, 6-2\n2002  Juan Carlos Ferrero bt. Carlos Moya 7-5, 6-3, 6-4\n2001  Gustavo Kuerten bt. Hicham Arazi 6-3, 6-2, 6-4\n2000  Cedric Pioline bt. Dominik Hrbaty 6-4, 7-6, 7-6",
								"stats": [
									]
							}
						}
				
				
			
				
				
				
				
				
			
			
			
			]
		}
	}
}
